setup.py
uasyncio.py
micropython_cpython_uasyncio.egg-info/PKG-INFO
micropython_cpython_uasyncio.egg-info/SOURCES.txt
micropython_cpython_uasyncio.egg-info/dependency_links.txt
micropython_cpython_uasyncio.egg-info/top_level.txt