Metadata-Version: 1.0
Name: micropython-cpython-uasyncio
Version: 0.1
Summary: MicroPython module uasyncio ported to CPython
Home-page: https://github.com/micropython/micropython/issues/405
Author: MicroPython Developers
Author-email: micro-python@googlegroups.com
License: Python
Platform: UNKNOWN
